LICENSE.txt
MANIFEST.in
README.md
setup.cfg
setup.py
PicMsgToExcel/PicMsgToExcel.pyd
PicMsgToExcel/PicMsgToExcelExecuter.pyd
PicMsgToExcel/__init__.py
PicMsgToExcel.egg-info/PKG-INFO
PicMsgToExcel.egg-info/SOURCES.txt
PicMsgToExcel.egg-info/dependency_links.txt
PicMsgToExcel.egg-info/top_level.txt
PicMsgToExcel/package/__init__.py
PicMsgToExcel/package/xlsxwriter/__init__.py
PicMsgToExcel/package/xlsxwriter/app.py
PicMsgToExcel/package/xlsxwriter/chart.py
PicMsgToExcel/package/xlsxwriter/chart_area.py
PicMsgToExcel/package/xlsxwriter/chart_bar.py
PicMsgToExcel/package/xlsxwriter/chart_column.py
PicMsgToExcel/package/xlsxwriter/chart_doughnut.py
PicMsgToExcel/package/xlsxwriter/chart_line.py
PicMsgToExcel/package/xlsxwriter/chart_pie.py
PicMsgToExcel/package/xlsxwriter/chart_radar.py
PicMsgToExcel/package/xlsxwriter/chart_scatter.py
PicMsgToExcel/package/xlsxwriter/chart_stock.py
PicMsgToExcel/package/xlsxwriter/chartsheet.py
PicMsgToExcel/package/xlsxwriter/comments.py
PicMsgToExcel/package/xlsxwriter/contenttypes.py
PicMsgToExcel/package/xlsxwriter/core.py
PicMsgToExcel/package/xlsxwriter/custom.py
PicMsgToExcel/package/xlsxwriter/drawing.py
PicMsgToExcel/package/xlsxwriter/exceptions.py
PicMsgToExcel/package/xlsxwriter/format.py
PicMsgToExcel/package/xlsxwriter/metadata.py
PicMsgToExcel/package/xlsxwriter/packager.py
PicMsgToExcel/package/xlsxwriter/relationships.py
PicMsgToExcel/package/xlsxwriter/shape.py
PicMsgToExcel/package/xlsxwriter/sharedstrings.py
PicMsgToExcel/package/xlsxwriter/styles.py
PicMsgToExcel/package/xlsxwriter/table.py
PicMsgToExcel/package/xlsxwriter/theme.py
PicMsgToExcel/package/xlsxwriter/utility.py
PicMsgToExcel/package/xlsxwriter/vml.py
PicMsgToExcel/package/xlsxwriter/workbook.py
PicMsgToExcel/package/xlsxwriter/worksheet.py
PicMsgToExcel/package/xlsxwriter/xmlwriter.py