Metadata-Version: 2.1
Name: PicMsgToExcel
Version: 0.1.8
Summary: OCR图片并将结果保存到Excel
Home-page: https://alidocs.dingtalk.com/i/p/4oJRz0VRJyvmLZMydy0mV7WvjQn7MG89
Author: likun
Author-email: 17891967090@163.com
Classifier: Programming Language :: Python
Requires-Python: >=3.8
License-File: LICENSE.txt
